awx_junit/__init__.py
awx_junit/awx_junit.py
awx_junit-1.1.dist-info/LICENSE
awx_junit-1.1.dist-info/METADATA
awx_junit-1.1.dist-info/WHEEL
awx_junit-1.1.dist-info/entry_points.txt
awx_junit-1.1.dist-info/top_level.txt
awx_junit-1.1.dist-info/RECORD
