Metadata-Version: 2.1
Name: awx-junit
Version: 1.1
Summary: A Ansible Tower or AWX utility to generate a JUnit XML report from a job.
Home-page: https://github.com/thushjandan/awx-junit
Author: Thushjandan Ponnudurai
Author-email: thushjandan@gmail.com
License: MIT
Platform: UNKNOWN
Classifier: Programming Language :: Python :: 3
Classifier: Programming Language :: Python :: 3.6
Classifier: Programming Language :: Python :: 3.7
Classifier: Programming Language :: Python :: 3.8
Classifier: Programming Language :: Python :: 3.9
Classifier: License :: OSI Approved :: MIT License
Classifier: Topic :: Software Development :: Build Tools
Classifier: Topic :: Software Development :: Testing
Requires-Dist: junit-xml
